internet_shop/__init__.py
internet_shop/admin.py
internet_shop/apps.py
internet_shop/cart.py
internet_shop/context_processors.py
internet_shop/urls.py
internet_shop/utils.py
internet_shop/views.py
internet_shop/locale/en/LC_MESSAGES/django.mo
internet_shop/locale/en/LC_MESSAGES/django.po
internet_shop/locale/ru/LC_MESSAGES/django.mo
internet_shop/locale/ru/LC_MESSAGES/django.po
internet_shop/migrations/0001_initial.py
internet_shop/migrations/0002_remove_cart_session_id_cart_session_key_and_more.py
internet_shop/migrations/__init__.py
internet_shop/migrations/__pycache__/0002_nikakix_decimal.cpython-314.pyc
internet_shop/migrations/__pycache__/0003_alter_product_price.cpython-314.pyc
internet_shop/migrations/__pycache__/0004_bolshe_nikakix_decimal.cpython-314.pyc
internet_shop/migrations/__pycache__/0005_remove_cart_products_remove_order_products_and_more.cpython-314.pyc
internet_shop/models/__init__.py
internet_shop/models/choices.py
internet_shop/models/default.py
internet_shop/static/internet_shop/js/cart.d.ts
internet_shop/static/internet_shop/js/cart.d.ts.map
internet_shop/static/internet_shop/js/cart.js
internet_shop/static/internet_shop/js/cart.js.map
internet_shop/static/internet_shop/js/cart.ts
internet_shop/templates/internet_shop/cart.html
internet_shop/templates/internet_shop/svg/x.svg
hrendjango_internet_shop-0.1.1.dist-info/METADATA
hrendjango_internet_shop-0.1.1.dist-info/WHEEL
hrendjango_internet_shop-0.1.1.dist-info/top_level.txt
hrendjango_internet_shop-0.1.1.dist-info/RECORD
