Metadata-Version: 2.4
Name: hrendjango-internet-shop
Version: 0.1.1
Summary: HrenDjango add-on for creating an online store
Home-page: https://github.com/MagIlyasDOMA/hrendjango-internet-shop
Author: Маг Ильяс DOMA (MagIlyasDOMA)
Author-email: magilyas.doma.09@list.ru
License: MIT
Classifier: Development Status :: 3 - Alpha
Classifier: Intended Audience :: Developers
Classifier: Programming Language :: Python :: 3
Classifier: Programming Language :: Python :: 3.10
Classifier: Programming Language :: Python :: 3.11
Classifier: Programming Language :: Python :: 3.12
Classifier: Programming Language :: Python :: 3.13
Classifier: Programming Language :: Python :: 3.14
Classifier: Programming Language :: Python :: 3 :: Only
Requires-Python: >=3.10
Requires-Dist: django>=5.2.9
Requires-Dist: hrendjango>=0.1.1
Requires-Dist: hrendjango-auth-plus>=0.1.0
Requires-Dist: hrenpack>=2.3.0
Dynamic: author
Dynamic: author-email
Dynamic: classifier
Dynamic: home-page
Dynamic: license
Dynamic: requires-dist
Dynamic: requires-python
Dynamic: summary
